aiogo/__init__.py
aiogo/py.typed
aiogo-0.2.0.dist-info/LICENSE.md
aiogo-0.2.0.dist-info/METADATA
aiogo-0.2.0.dist-info/WHEEL
aiogo-0.2.0.dist-info/RECORD
