Metadata-Version: 2.1
Name: aiogo
Version: 0.2.0
Summary: Tiny helper for running your async code
Home-page: https://github.com/zzzzlzzzz/aiorun
License: MIT
Author: tony9152273
Author-email: 9152273+zzzzlzzzz@users.noreply.github.com
Requires-Python: >=3.10,<4.0
Classifier: Framework :: AsyncIO
Classifier: License :: OSI Approved :: MIT License
Classifier: Operating System :: OS Independent
Classifier: Programming Language :: Python :: 3
Classifier: Programming Language :: Python :: 3.10
Classifier: Programming Language :: Python :: 3.11
Classifier: Programming Language :: Python :: 3.12
Classifier: Programming Language :: Python :: 3.13
Provides-Extra: ci
Requires-Dist: mypy (>=1.14.1,<2.0.0) ; extra == "ci"
Requires-Dist: pre-commit (>=4.0.1,<5.0.0) ; extra == "ci"
Requires-Dist: pytest (>=8.3.4,<9.0.0) ; extra == "ci"
Requires-Dist: pytest-xdist (>=3.6.1,<4.0.0) ; extra == "ci"
Requires-Dist: ruff (>=0.8.5,<0.9.0) ; extra == "ci"
Project-URL: Repository, https://github.com/zzzzlzzzz/aiorun
